{"data":{"markdownRemark":{"html":"<p><img src=\"https://www.subtraction.com/wp-content/uploads/2016/03/2016-03-24-lingo.png\"></p>\n<p><a href=\"https://www.subtraction.com/2016/03/24/lingo-by-noun-project/\">Khoi Vinh, writing about Lingo by Noun Project</a>:</p>\n<blockquote>\n<p>Designers can drag and drop their assets into Lingo’s thumbnail browser interface; the assets are synced to Lingo’s own cloud service and are then accessible across computers. </p>\n</blockquote>\n<p>This looks very promising.</p>","frontmatter":{"pretitle":null,"title":"Lingo","date":"2016-03-25"}}},"pageContext":{"isCreatedByStatefulCreatePages":false,"slug":"/articles/2016-03-25-lingo/"}}